almonds
