Metadata-Version: 1.1
Name: almonds
Version: 1.25b
Summary: Terminal fractal viewer
Home-page: https://github.com/Tenchi2xh/Almonds
Author: Tenchi
Author-email: tenkage@gmail.com
License: UNKNOWN
Download-URL: https://github.com/Tenchi2xh/Almonds/tarball/1.25b
Keywords: fractal,mandelbrot,terminal,termbox,curses
Platform: UNKNOWN
Classifier: Development Status :: 4 - Beta
Classifier: Programming Language :: Python :: 2.6
Classifier: Programming Language :: Python :: 2.7
Classifier: Programming Language :: Python :: 3.3
Classifier: Programming Language :: Python :: 3.4
Classifier: Programming Language :: Python :: 3.5
